{
          "status": "OK",
          "usage": "By accessing AlchemyAPI or using information generated by AlchemyAPI, you are agreeing to be bound by the AlchemyAPI Terms of Use: http://www.alchemyapi.com/company/terms.html",
          "language": "english",
          "concepts": [
                    {
                              "text": "Graph theory",
                              "relevance": "0.957028",
                              "dbpedia": "http://dbpedia.org/resource/Graph_theory",
                              "freebase": "http://rdf.freebase.com/ns/m.0382k",
                              "opencyc": "http://sw.opencyc.org/concept/Mx4rvt3YbJwpEbGdrcN5Y29ycA"
                    },
                    {
                              "text": "Perfect graph",
                              "relevance": "0.730053",
                              "dbpedia": "http://dbpedia.org/resource/Perfect_graph",
                              "freebase": "http://rdf.freebase.com/ns/m.031hx5",
                              "yago": "http://yago-knowledge.org/resource/Perfect_graph"
                    },
                    {
                              "text": "Graph coloring",
                              "relevance": "0.709852",
                              "dbpedia": "http://dbpedia.org/resource/Graph_coloring",
                              "freebase": "http://rdf.freebase.com/ns/m.02749z",
                              "yago": "http://yago-knowledge.org/resource/Graph_coloring"
                    },
                    {
                              "text": "Bipartite graph",
                              "relevance": "0.541105",
                              "dbpedia": "http://dbpedia.org/resource/Bipartite_graph",
                              "freebase": "http://rdf.freebase.com/ns/m.01kdsb",
                              "yago": "http://yago-knowledge.org/resource/Bipartite_graph"
                    },
                    {
                              "text": "Mathematics",
                              "relevance": "0.502746",
                              "dbpedia": "http://dbpedia.org/resource/Mathematics",
                              "freebase": "http://rdf.freebase.com/ns/m.04rjg",
                              "opencyc": "http://sw.opencyc.org/concept/Mx4rvVjHd5wpEbGdrcN5Y29ycA"
                    },
                    {
                              "text": "Computer graphics",
                              "relevance": "0.480966",
                              "dbpedia": "http://dbpedia.org/resource/Computer_graphics",
                              "freebase": "http://rdf.freebase.com/ns/m.01xfp"
                    },
                    {
                              "text": "Greedy coloring",
                              "relevance": "0.453123",
                              "dbpedia": "http://dbpedia.org/resource/Greedy_coloring",
                              "freebase": "http://rdf.freebase.com/ns/m.05b62q1"
                    },
                    {
                              "text": "Planar graph",
                              "relevance": "0.434802",
                              "dbpedia": "http://dbpedia.org/resource/Planar_graph",
                              "freebase": "http://rdf.freebase.com/ns/m.062b_",
                              "yago": "http://yago-knowledge.org/resource/Planar_graph"
                    }
          ]
}