{
          "status": "OK",
          "usage": "By accessing AlchemyAPI or using information generated by AlchemyAPI, you are agreeing to be bound by the AlchemyAPI Terms of Use: http://www.alchemyapi.com/company/terms.html",
          "language": "english",
          "concepts": [
                    {
                              "text": "Cathay Pacific",
                              "relevance": "0.989324",
                              "website": "http://cathaypacific.com",
                              "dbpedia": "http://dbpedia.org/resource/Cathay_Pacific",
                              "freebase": "http://rdf.freebase.com/ns/m.013qmk",
                              "yago": "http://yago-knowledge.org/resource/Cathay_Pacific"
                    },
                    {
                              "text": "Airline",
                              "relevance": "0.852899",
                              "dbpedia": "http://dbpedia.org/resource/Airline",
                              "freebase": "http://rdf.freebase.com/ns/m.0vg8",
                              "opencyc": "http://sw.opencyc.org/concept/Mx4r70O0wMBoQdeNIZE2z_cagA"
                    },
                    {
                              "text": "Flag carrier",
                              "relevance": "0.781633",
                              "dbpedia": "http://dbpedia.org/resource/Flag_carrier",
                              "freebase": "http://rdf.freebase.com/ns/m.02cvm1"
                    },
                    {
                              "text": "Malaysia Airlines",
                              "relevance": "0.745286",
                              "website": "http://www.malaysiaairlines.com",
                              "dbpedia": "http://dbpedia.org/resource/Malaysia_Airlines",
                              "freebase": "http://rdf.freebase.com/ns/m.013_0l",
                              "yago": "http://yago-knowledge.org/resource/Malaysia_Airlines"
                    },
                    {
                              "text": "Oneworld",
                              "relevance": "0.740566",
                              "website": "http://oneworld.com",
                              "dbpedia": "http://dbpedia.org/resource/Oneworld",
                              "freebase": "http://rdf.freebase.com/ns/m.01qynv",
                              "yago": "http://yago-knowledge.org/resource/Oneworld"
                    },
                    {
                              "text": "Philippine Airlines",
                              "relevance": "0.717177",
                              "website": "http://www.philippineairlines.com",
                              "dbpedia": "http://dbpedia.org/resource/Philippine_Airlines",
                              "freebase": "http://rdf.freebase.com/ns/m.01rcct",
                              "yago": "http://yago-knowledge.org/resource/Philippine_Airlines"
                    },
                    {
                              "text": "Air New Zealand",
                              "relevance": "0.674484",
                              "website": "http://www.airnewzealand.co.nz",
                              "dbpedia": "http://dbpedia.org/resource/Air_New_Zealand",
                              "freebase": "http://rdf.freebase.com/ns/m.011lt8",
                              "yago": "http://yago-knowledge.org/resource/Air_New_Zealand"
                    },
                    {
                              "text": "Cargo airline",
                              "relevance": "0.657788",
                              "dbpedia": "http://dbpedia.org/resource/Cargo_airline",
                              "freebase": "http://rdf.freebase.com/ns/m.0p_w4"
                    }
          ]
}